{
  "response": {
    "success": true,
    "message": "Fetching  Data  Request Succeeded: Email",
    "data": [
      {
        "from": "Araf Karsh Hamid",
        "title": "Angular MetaMagic Extension Release Plans (AMEXIO)",
        "date": "21-07-2017"
      },
      {
        "from": "Araf Karsh Hamid",
        "title": " Amexio Visual Studio Code Extension - Published",
        "date": "21-07-2017"
      },
      {
        "from": "Ketan Gote",
        "title": "Amexio on angular.io",
        "date": "21-07-2017"
      },
      {
        "from": "Araf Karsh Hamid",
        "title": "Amexio NPM Download Spike",
        "date": "22-07-2017"
      },{
        "from": "Dattaram Gawas",
        "title": "Building Web Components with TypeScript and Angular 4",
        "date": "20-07-2017"
      },
      {
        "from": "Sagar Jadhav",
        "title": "Showcase App URL",
        "date": "20-07-2017"
      },
      {
        "from": "Ketan Gote",
        "title": "Spring cloud stream demo",
        "date": "19-07-2017"
      },
      {
        "from": "Ketan Gote",
        "title": "Spring Microservice demo",
        "date": "19-07-2017"
      },
      {
        "from": "Ketan Gote",
        "title": "Spring cloud stream Kafka Integration",
        "date": "18-07-2017"
      },
      {
        "from": "Ashutosh Jadhav",
        "title": "JSR Implementation",
        "date": "18-07-2017"
      },
      {
        "from": "Mahesh Pardeshi",
        "title": "AXON CQRS demo",
        "date": "17-07-2017"
      },
      {
        "from": "Pratik Kelwalkar",
        "title": "Angular Routing",
        "date": "17-07-2017"
      },
      {
        "from": "Dattaram Gawas",
        "title": "Angular Pipes",
        "date": "16-07-2017"
      },
      {
        "from": "Ketan Gote",
        "title": "Ribbon, Hysterix Using Spring Feign",
        "date": "15-07-2017"
      },
      {
        "from": "Ketan Gote",
        "title": "Eureka server using spring cloud",
        "date": "14-07-2017"
      },
      {
        "from": "Mahesh Pardeshi",
        "title": "RX Java",
        "date": "14-07-2017"
      },
      {
        "from": "Anagha Kulkarni",
        "title": "Spring + Mongo DB",
        "date": "13-07-2017"
      },{
        "from": "Araf Karsh Hamid",
        "title": "Flux / Redux Architecture - Kreative Kanvas",
        "date": "11-07-2017"
      },{
        "from": "Ketan Gote",
        "title": "Desire Platform GIT repos",
        "date": "11-07-2017"
      },{
        "from": "Pratik Kelwalkar",
        "title": "mobile.twitter.com PWA from React to Angular/Ionic",
        "date": "10-07-2017"
      },{
        "from": "Ketan Gote",
        "title": "Messages in Platform",
        "date": "10-07-2017"
      },{
        "from": "Araf Karsh Hamid",
        "title": "TypeScript - Angular's Secret Weapon...",
        "date": "09-07-2017"
      },{
        "from": "Araf Karsh Hamid",
        "title": "Visual Studio Code - Plugin for Amexio",
        "date": "09-07-2017"
      },{
        "from": "Ketan Gote",
        "title": "Hashing Algo",
        "date": "08-07-2017"
      },{
        "from": "Araf Karsh Hamid",
        "title": "Visual Studio Code for Windows, Linux and Mac OS",
        "date": "07-07-2017"
      },{
        "from": "Araf Karsh Hamid",
        "title": "Chart Library - Open Source",
        "date": "06-07-2017"
      },{
        "from": "Ketan Gote",
        "title": "The mechanics of DOM updates in Angular",
        "date": "06-07-2017"
      },{
        "from": "Araf Karsh Hamid",
        "title": "Amexio Release v0.02 Release - Hampi",
        "date": "05-07-2017"
      },{
        "from": "Pratik Kelwalkar",
        "title": "Building Web Components with TypeScript and Angular 4",
        "date": "05-07-2017"
      },{
        "from": "Ketan Gote",
        "title": "Sample Spring + Redis Integration Project",
        "date": "05-07-2017"
      },{
        "from": "Araf Karsh Hamid",
        "title": "Angular MetaMagic Extension Release Plans (AMEXIO)",
        "date": "04-07-2017"
      }
    ]
  }
}
